mailhog/__init__.py
mailhog/extension.py
mailhog/package.py
mailhog/server.py
localstack_extension_mailhog-0.2.0.dist-info/METADATA
localstack_extension_mailhog-0.2.0.dist-info/WHEEL
localstack_extension_mailhog-0.2.0.dist-info/entry_points.txt
localstack_extension_mailhog-0.2.0.dist-info/top_level.txt
localstack_extension_mailhog-0.2.0.dist-info/RECORD
