Metadata-Version: 2.1
Name: localstack-extension-mailhog
Version: 0.2.0
Summary: LocalStack Extension: MailHog
Home-page: https://github.com/localstack/localstack-extensions/tree/main/mailhog
Author: LocalStack
Author-email: info@localstack.cloud
Provides-Extra: dev
Requires-Dist: localstack-core>=2.2; extra == "dev"
